azure_switchboard/__init__.py
azure_switchboard/deployment.py
azure_switchboard/model.py
azure_switchboard/py.typed
azure_switchboard/switchboard.py
azure_switchboard-2025.9.0.dist-info/METADATA
azure_switchboard-2025.9.0.dist-info/WHEEL
azure_switchboard-2025.9.0.dist-info/licenses/LICENSE
azure_switchboard-2025.9.0.dist-info/RECORD
