Metadata-Version: 2.4
Name: azure-switchboard
Version: 2025.9.0
Summary: Batteries-included loadbalancing client for Azure OpenAI
Project-URL: Homepage, https://github.com/arini-ai/azure-switchboard
Author-email: Abizer Lokhandwala <abizer@abizer.me>
License: MIT
License-File: LICENSE
Keywords: ai,azure,litellm,llm,loadbalancing,openai
Classifier: License :: OSI Approved :: MIT License
Classifier: Programming Language :: Python :: 3
Classifier: Programming Language :: Python :: 3.10
Classifier: Programming Language :: Python :: 3.11
Classifier: Programming Language :: Python :: 3.12
Classifier: Topic :: Scientific/Engineering :: Artificial Intelligence
Requires-Python: >=3.10
Requires-Dist: openai>=1.62.0
Requires-Dist: opentelemetry-api>=1.30.0
Requires-Dist: tenacity>=9.0.0
Requires-Dist: wrapt>=1.17.2
